LICENSE
MANIFEST.in
README.txt
setup.py
atomisator/__init__.py
atomisator.filters.egg-info/PKG-INFO
atomisator.filters.egg-info/SOURCES.txt
atomisator.filters.egg-info/dependency_links.txt
atomisator.filters.egg-info/entry_points.txt
atomisator.filters.egg-info/namespace_packages.txt
atomisator.filters.egg-info/not-zip-safe
atomisator.filters.egg-info/requires.txt
atomisator.filters.egg-info/top_level.txt
atomisator/filters/__init__.py
atomisator/filters/followers.py
atomisator/filters/todo.txt
atomisator/filters/guess_language/Blocks.txt
atomisator/filters/guess_language/COPYING.txt
atomisator/filters/guess_language/__init__.py
atomisator/filters/guess_language/blocks.py
atomisator/filters/guess_language/blocks_test.py
atomisator/filters/guess_language/guess_language.py
atomisator/filters/guess_language/guess_language_test.py
atomisator/filters/guess_language/trigrams/af
atomisator/filters/guess_language/trigrams/ar
atomisator/filters/guess_language/trigrams/az
atomisator/filters/guess_language/trigrams/bg
atomisator/filters/guess_language/trigrams/ca
atomisator/filters/guess_language/trigrams/ceb
atomisator/filters/guess_language/trigrams/cs
atomisator/filters/guess_language/trigrams/cy
atomisator/filters/guess_language/trigrams/da
atomisator/filters/guess_language/trigrams/de
atomisator/filters/guess_language/trigrams/en
atomisator/filters/guess_language/trigrams/es
atomisator/filters/guess_language/trigrams/et
atomisator/filters/guess_language/trigrams/eu
atomisator/filters/guess_language/trigrams/fa
atomisator/filters/guess_language/trigrams/fi
atomisator/filters/guess_language/trigrams/fr
atomisator/filters/guess_language/trigrams/ha
atomisator/filters/guess_language/trigrams/haw
atomisator/filters/guess_language/trigrams/hi
atomisator/filters/guess_language/trigrams/hr
atomisator/filters/guess_language/trigrams/hu
atomisator/filters/guess_language/trigrams/id
atomisator/filters/guess_language/trigrams/is
atomisator/filters/guess_language/trigrams/it
atomisator/filters/guess_language/trigrams/kk
atomisator/filters/guess_language/trigrams/ky
atomisator/filters/guess_language/trigrams/la
atomisator/filters/guess_language/trigrams/lt
atomisator/filters/guess_language/trigrams/lv
atomisator/filters/guess_language/trigrams/mk
atomisator/filters/guess_language/trigrams/mn
