Metadata-Version: 1.0
Name: atomisator.filters
Version: 0.2.1
Summary: Expert Python Programming - Filters
Home-page: http://atomisator.ziade.org
Author: Tarek Ziade
Author-email: tarek@ziade.org
License: GPL
Keywords: python best practices
Platform: UNKNOWN
Classifier: Programming Language :: Python
Classifier: Topic :: Software Development :: Libraries :: Python Modules
